enova/algo/__init__.py
enova/algo/resource.py
enova/algo/serializer.py
enova/algo/server.py
enova/algo/service.py
enova/api/__init__.py
enova/api/app_api.py
enova/api/base.py
enova/api/escaler_api.py
enova/api/prom_api.py
enova/api/serving_api.py
enova/app/__init__.py
enova/app/db_modles.py
enova/app/resource.py
enova/app/serializer.py
enova/app/server.py
enova/app/service.py
enova/app/utils.py
enova/common/__init__.py
enova/common/cli_helper.py
enova/common/config.py
enova/common/constant.py
enova/common/encoder.py
enova/common/error.py
enova/common/g_vars.py
enova/common/local.py
enova/common/logger.py
enova/common/utils.py
enova/database/__init__.py
enova/database/relation/__init__.py
enova/database/relation/orm/__init__.py
enova/database/relation/orm/base.py
enova/database/relation/transaction/__init__.py
enova/database/relation/transaction/session.py
enova/entry/cli.py
enova/entry/command/__init__.py
enova/entry/command/algo.py
enova/entry/command/app.py
enova/entry/command/injector.py
enova/entry/command/mon.py
enova/entry/command/pilot.py
enova/entry/command/serving.py
enova/entry/command/webui.py
enova/job/__init__.py
enova/job/job_manager.py
enova/server/__init__.py
enova/server/server.py
enova/server/exception/__init__.py
enova/server/exception/handler.py
enova/server/middleware/__init__.py
enova/server/middleware/base.py
enova/server/middleware/response.py
enova/server/middleware/trace.py
enova/server/restful/__init__.py
enova/server/restful/router.py
enova/server/restful/serializer.py
enova/server/restful/service.py
enova/serving/__init__.py
enova/serving/apiserver.py
enova/serving/backend/base.py
enova/serving/backend/injector.py
enova/serving/backend/transformers.py
enova/serving/backend/utils.py
enova/serving/backend/vllm.py
enova/serving/backend/hf/__init__.py
enova/serving/backend/hf/handler.py
enova/serving/backend/hf/hf.py
enova/serving/middlewares/auth.py
enova/serving/middlewares/base.py
enova/serving/middlewares/cors.py
enova-0.0.7.dist-info/LICENSE
enova-0.0.7.dist-info/METADATA
enova-0.0.7.dist-info/WHEEL
enova-0.0.7.dist-info/entry_points.txt
enova-0.0.7.dist-info/top_level.txt
enova-0.0.7.dist-info/RECORD
