Metadata-Version: 2.1
Name: enova
Version: 0.0.7
Summary: enova
Author-email: kyokagong <kyokagong@emergingai-tech.com>, wenxinxie <wenxin@emergingai-tech.com>, jockyhawk <jockyhawk@emergingai-tech.com>, kimzhao <kimzhao@emergingai-tech.com>
Requires-Python: >=3.8
License-File: LICENSE
Requires-Dist: httpx ==0.24.1
Requires-Dist: fastapi ==0.108.0
Requires-Dist: huggingface-hub
Requires-Dist: hf-transfer
Requires-Dist: transformers
Requires-Dist: locate
Requires-Dist: python-rapidjson
Requires-Dist: opentelemetry-api
Requires-Dist: opentelemetry-sdk
Requires-Dist: opentelemetry-exporter-otlp
Requires-Dist: opentelemetry-distro
Requires-Dist: opentelemetry-instrumentation-fastapi
Requires-Dist: streamlit
Requires-Dist: pymysql ==1.1.0
Requires-Dist: aiomysql ==0.2.0
Requires-Dist: sqlalchemy ==2.0.29
Requires-Dist: sqlalchemy-utils
Requires-Dist: aiosqlite
Requires-Dist: greenlet
Requires-Dist: uvicorn
Requires-Dist: ulid-py
Requires-Dist: pyopencl
Requires-Dist: py-cpuinfo
Requires-Dist: pytz
Requires-Dist: tzlocal
Requires-Dist: openai
Requires-Dist: packaging
Requires-Dist: ray
Requires-Dist: enova-instrumentation-llmo ==0.0.7
Requires-Dist: addict
Provides-Extra: lint
Requires-Dist: black ==23.12.0 ; extra == 'lint'
Provides-Extra: test
Requires-Dist: pytest ; extra == 'test'
Requires-Dist: pytest-cov ; extra == 'test'
Requires-Dist: responses ; extra == 'test'
Requires-Dist: respx ; extra == 'test'
